{
  "generated_at": "2026-06-13T08:00:44.357479+00:00",
  "trend_days": 14,
  "markets": {
    "CPI": {
      "contract_series": "KXCPIYOY-26JUN",
      "latest_run": "2026-06-13T08:00:06.062947+00:00",
      "implied_mean": 3.884,
      "std_dev": 0.2877,
      "skewness": -2.2853,
      "market_volume_usd": 126342.0,
      "days_to_event": 31,
      "trend": [
        {
          "timestamp": "2026-05-30T14:00:00.763285+00:00",
          "implied_mean": 4.2045,
          "std_dev": 0.2447,
          "skewness": -4.6414
        },
        {
          "timestamp": "2026-05-30T20:00:00.612362+00:00",
          "implied_mean": 4.1995,
          "std_dev": 0.2467,
          "skewness": -4.4762
        },
        {
          "timestamp": "2026-05-31T02:00:00.812212+00:00",
          "implied_mean": 4.1985,
          "std_dev": 0.2451,
          "skewness": -4.5623
        },
        {
          "timestamp": "2026-05-31T08:00:00.964058+00:00",
          "implied_mean": 4.1985,
          "std_dev": 0.2451,
          "skewness": -4.5623
        },
        {
          "timestamp": "2026-05-31T14:00:01.418772+00:00",
          "implied_mean": 4.1925,
          "std_dev": 0.247,
          "skewness": -4.3944
        },
        {
          "timestamp": "2026-05-31T20:00:01.591951+00:00",
          "implied_mean": 4.1965,
          "std_dev": 0.2447,
          "skewness": -4.5478
        },
        {
          "timestamp": "2026-06-01T02:00:05.631255+00:00",
          "implied_mean": 4.2015,
          "std_dev": 0.2447,
          "skewness": -4.6071
        },
        {
          "timestamp": "2026-06-01T08:00:00.435070+00:00",
          "implied_mean": 4.2005,
          "std_dev": 0.2455,
          "skewness": -4.5533
        },
        {
          "timestamp": "2026-06-01T14:00:01.532592+00:00",
          "implied_mean": 4.1925,
          "std_dev": 0.2454,
          "skewness": -4.4672
        },
        {
          "timestamp": "2026-06-01T20:00:05.112607+00:00",
          "implied_mean": 4.1925,
          "std_dev": 0.2388,
          "skewness": -4.889
        },
        {
          "timestamp": "2026-06-02T02:00:01.395096+00:00",
          "implied_mean": 4.1875,
          "std_dev": 0.2398,
          "skewness": -4.752
        },
        {
          "timestamp": "2026-06-02T08:00:01.384066+00:00",
          "implied_mean": 4.1855,
          "std_dev": 0.2376,
          "skewness": -4.9016
        },
        {
          "timestamp": "2026-06-02T14:00:01.758389+00:00",
          "implied_mean": 4.1885,
          "std_dev": 0.2378,
          "skewness": -4.9331
        },
        {
          "timestamp": "2026-06-02T20:00:04.326511+00:00",
          "implied_mean": 4.1915,
          "std_dev": 0.2383,
          "skewness": -4.9204
        },
        {
          "timestamp": "2026-06-03T02:00:01.016574+00:00",
          "implied_mean": 4.1965,
          "std_dev": 0.2401,
          "skewness": -4.8491
        },
        {
          "timestamp": "2026-06-03T08:00:04.863048+00:00",
          "implied_mean": 4.1935,
          "std_dev": 0.2409,
          "skewness": -4.7785
        },
        {
          "timestamp": "2026-06-03T14:00:02.931050+00:00",
          "implied_mean": 4.1875,
          "std_dev": 0.2407,
          "skewness": -4.719
        },
        {
          "timestamp": "2026-06-03T20:00:04.396391+00:00",
          "implied_mean": 4.1745,
          "std_dev": 0.2367,
          "skewness": -4.8316
        },
        {
          "timestamp": "2026-06-04T02:00:05.558270+00:00",
          "implied_mean": 4.1735,
          "std_dev": 0.2357,
          "skewness": -4.8898
        },
        {
          "timestamp": "2026-06-04T08:00:01.826168+00:00",
          "implied_mean": 4.1785,
          "std_dev": 0.2371,
          "skewness": -4.8432
        },
        {
          "timestamp": "2026-06-04T14:00:04.825699+00:00",
          "implied_mean": 4.1775,
          "std_dev": 0.2366,
          "skewness": -4.8793
        },
        {
          "timestamp": "2026-06-04T20:00:02.015947+00:00",
          "implied_mean": 4.1785,
          "std_dev": 0.2379,
          "skewness": -4.7945
        },
        {
          "timestamp": "2026-06-05T02:00:05.139466+00:00",
          "implied_mean": 4.1745,
          "std_dev": 0.2392,
          "skewness": -4.6737
        },
        {
          "timestamp": "2026-06-05T08:00:05.406934+00:00",
          "implied_mean": 4.1785,
          "std_dev": 0.2272,
          "skewness": -4.7805
        },
        {
          "timestamp": "2026-06-05T14:00:05.529464+00:00",
          "implied_mean": 4.1765,
          "std_dev": 0.2257,
          "skewness": -4.8529
        },
        {
          "timestamp": "2026-06-05T20:00:03.259677+00:00",
          "implied_mean": 4.1805,
          "std_dev": 0.2252,
          "skewness": -4.94
        },
        {
          "timestamp": "2026-06-06T02:00:02.750302+00:00",
          "implied_mean": 4.1825,
          "std_dev": 0.2275,
          "skewness": -4.8206
        },
        {
          "timestamp": "2026-06-06T08:00:05.063210+00:00",
          "implied_mean": 4.1885,
          "std_dev": 0.2279,
          "skewness": -4.8432
        },
        {
          "timestamp": "2026-06-06T14:00:04.115414+00:00",
          "implied_mean": 4.1895,
          "std_dev": 0.2271,
          "skewness": -4.8595
        },
        {
          "timestamp": "2026-06-06T20:00:05.989113+00:00",
          "implied_mean": 4.1885,
          "std_dev": 0.2261,
          "skewness": -4.8974
        },
        {
          "timestamp": "2026-06-07T02:00:03.141352+00:00",
          "implied_mean": 4.1925,
          "std_dev": 0.2263,
          "skewness": -4.9386
        },
        {
          "timestamp": "2026-06-07T08:00:04.590402+00:00",
          "implied_mean": 4.1895,
          "std_dev": 0.224,
          "skewness": -5.0602
        },
        {
          "timestamp": "2026-06-07T14:00:03.779191+00:00",
          "implied_mean": 4.1915,
          "std_dev": 0.2241,
          "skewness": -5.0914
        },
        {
          "timestamp": "2026-06-07T20:00:04.873686+00:00",
          "implied_mean": 4.1865,
          "std_dev": 0.2234,
          "skewness": -5.0815
        },
        {
          "timestamp": "2026-06-08T02:00:05.484895+00:00",
          "implied_mean": 4.1875,
          "std_dev": 0.223,
          "skewness": -5.114
        },
        {
          "timestamp": "2026-06-08T08:00:05.061809+00:00",
          "implied_mean": 4.1845,
          "std_dev": 0.221,
          "skewness": -5.2386
        },
        {
          "timestamp": "2026-06-08T14:00:05.596057+00:00",
          "implied_mean": 4.1815,
          "std_dev": 0.2212,
          "skewness": -5.2016
        },
        {
          "timestamp": "2026-06-08T20:00:05.493883+00:00",
          "implied_mean": 4.1895,
          "std_dev": 0.2217,
          "skewness": -5.2155
        },
        {
          "timestamp": "2026-06-09T02:00:06.083278+00:00",
          "implied_mean": 4.1875,
          "std_dev": 0.2234,
          "skewness": -5.1338
        },
        {
          "timestamp": "2026-06-09T08:00:04.768805+00:00",
          "implied_mean": 4.196,
          "std_dev": 0.2448,
          "skewness": -3.1678
        },
        {
          "timestamp": "2026-06-09T14:00:04.970342+00:00",
          "implied_mean": 4.175,
          "std_dev": 0.2407,
          "skewness": -3.096
        },
        {
          "timestamp": "2026-06-09T20:00:05.165364+00:00",
          "implied_mean": 4.1855,
          "std_dev": 0.2201,
          "skewness": -5.3251
        },
        {
          "timestamp": "2026-06-10T02:00:05.357584+00:00",
          "implied_mean": 4.1865,
          "std_dev": 0.2287,
          "skewness": -4.7377
        },
        {
          "timestamp": "2026-06-10T08:00:00.946087+00:00",
          "implied_mean": 4.1885,
          "std_dev": 0.2261,
          "skewness": -4.9649
        },
        {
          "timestamp": "2026-06-10T14:00:05.466072+00:00",
          "implied_mean": 4.1085,
          "std_dev": 0.5757,
          "skewness": -1.9631
        },
        {
          "timestamp": "2026-06-10T20:00:06.379219+00:00",
          "implied_mean": 4.0435,
          "std_dev": 0.5773,
          "skewness": -1.6209
        },
        {
          "timestamp": "2026-06-11T02:00:05.752474+00:00",
          "implied_mean": 3.9845,
          "std_dev": 0.5407,
          "skewness": -1.7583
        },
        {
          "timestamp": "2026-06-11T08:00:06.014991+00:00",
          "implied_mean": 3.9645,
          "std_dev": 0.5314,
          "skewness": -1.762
        },
        {
          "timestamp": "2026-06-11T14:00:06.181430+00:00",
          "implied_mean": 3.9865,
          "std_dev": 0.541,
          "skewness": -1.7675
        },
        {
          "timestamp": "2026-06-11T20:00:04.232199+00:00",
          "implied_mean": 4.0775,
          "std_dev": 0.3438,
          "skewness": -1.8492
        },
        {
          "timestamp": "2026-06-12T02:00:06.027300+00:00",
          "implied_mean": 3.9655,
          "std_dev": 0.3409,
          "skewness": -1.2209
        },
        {
          "timestamp": "2026-06-12T08:00:06.232905+00:00",
          "implied_mean": 4.0105,
          "std_dev": 0.3624,
          "skewness": -1.1293
        },
        {
          "timestamp": "2026-06-12T14:00:05.441161+00:00",
          "implied_mean": 3.971,
          "std_dev": 0.3326,
          "skewness": -1.4976
        },
        {
          "timestamp": "2026-06-12T20:00:01.621394+00:00",
          "implied_mean": 3.89,
          "std_dev": 0.281,
          "skewness": -2.526
        },
        {
          "timestamp": "2026-06-13T02:00:04.953326+00:00",
          "implied_mean": 3.883,
          "std_dev": 0.2887,
          "skewness": -2.2468
        },
        {
          "timestamp": "2026-06-13T08:00:06.062947+00:00",
          "implied_mean": 3.884,
          "std_dev": 0.2877,
          "skewness": -2.2853
        }
      ],
      "distribution": [
        {
          "label": "3.8%\u20133.9%",
          "strike": 3.8,
          "probability": 0.3,
          "yes_price": 0.66,
          "volume": 0
        },
        {
          "label": "3.7%\u20133.8%",
          "strike": 3.7,
          "probability": 0.28,
          "yes_price": 0.94,
          "volume": 0
        },
        {
          "label": "2.7%\u20132.8%",
          "strike": 2.7,
          "probability": 0.1,
          "yes_price": 0.99,
          "volume": 0
        }
      ],
      "label": "CPI (YoY)",
      "is_probability": false,
      "annotations": [
        {
          "event_date": "2026-06-10",
          "label": "CPI (May)",
          "type": "cpi",
          "notes": "",
          "is_past": true
        },
        {
          "event_date": "2026-07-14",
          "label": "CPI (Jun)",
          "type": "cpi",
          "notes": "",
          "is_past": false
        },
        {
          "event_date": "2026-08-12",
          "label": "CPI (Jul)",
          "type": "cpi",
          "notes": "",
          "is_past": false
        },
        {
          "event_date": "2026-09-11",
          "label": "CPI (Aug)",
          "type": "cpi",
          "notes": "",
          "is_past": false
        },
        {
          "event_date": "2026-10-14",
          "label": "CPI (Sep)",
          "type": "cpi",
          "notes": "",
          "is_past": false
        },
        {
          "event_date": "2026-11-10",
          "label": "CPI (Oct)",
          "type": "cpi",
          "notes": "",
          "is_past": false
        },
        {
          "event_date": "2026-12-10",
          "label": "CPI (Nov)",
          "type": "cpi",
          "notes": "",
          "is_past": false
        }
      ]
    },
    "Core_CPI_MoM": {
      "contract_series": "KXCPICORE-26JUN",
      "latest_run": "2026-06-13T08:00:06.062947+00:00",
      "implied_mean": 0.179,
      "std_dev": 0.2111,
      "skewness": 2.0831,
      "market_volume_usd": 7196.0,
      "days_to_event": 31,
      "trend": [
        {
          "timestamp": "2026-05-30T14:00:00.763285+00:00",
          "implied_mean": 0.223,
          "std_dev": 0.205,
          "skewness": 3.127
        },
        {
          "timestamp": "2026-05-30T20:00:00.612362+00:00",
          "implied_mean": 0.223,
          "std_dev": 0.205,
          "skewness": 3.127
        },
        {
          "timestamp": "2026-05-31T02:00:00.812212+00:00",
          "implied_mean": 0.223,
          "std_dev": 0.205,
          "skewness": 3.127
        },
        {
          "timestamp": "2026-05-31T08:00:00.964058+00:00",
          "implied_mean": 0.224,
          "std_dev": 0.2044,
          "skewness": 3.1457
        },
        {
          "timestamp": "2026-05-31T14:00:01.418772+00:00",
          "implied_mean": 0.226,
          "std_dev": 0.2056,
          "skewness": 3.0742
        },
        {
          "timestamp": "2026-05-31T20:00:01.591951+00:00",
          "implied_mean": 0.229,
          "std_dev": 0.2052,
          "skewness": 3.05
        },
        {
          "timestamp": "2026-06-01T02:00:05.631255+00:00",
          "implied_mean": 0.23,
          "std_dev": 0.2051,
          "skewness": 3.0423
        },
        {
          "timestamp": "2026-06-01T08:00:00.435070+00:00",
          "implied_mean": 0.234,
          "std_dev": 0.2064,
          "skewness": 2.9339
        },
        {
          "timestamp": "2026-06-01T14:00:01.532592+00:00",
          "implied_mean": 0.231,
          "std_dev": 0.2054,
          "skewness": 3.0147
        },
        {
          "timestamp": "2026-06-01T20:00:05.112607+00:00",
          "implied_mean": 0.224,
          "std_dev": 0.2024,
          "skewness": 3.2236
        },
        {
          "timestamp": "2026-06-02T02:00:01.395096+00:00",
          "implied_mean": 0.224,
          "std_dev": 0.2009,
          "skewness": 3.3047
        },
        {
          "timestamp": "2026-06-02T08:00:01.384066+00:00",
          "implied_mean": 0.224,
          "std_dev": 0.2009,
          "skewness": 3.3047
        },
        {
          "timestamp": "2026-06-02T14:00:01.758389+00:00",
          "implied_mean": 0.225,
          "std_dev": 0.2003,
          "skewness": 3.3266
        },
        {
          "timestamp": "2026-06-02T20:00:04.326511+00:00",
          "implied_mean": 0.219,
          "std_dev": 0.201,
          "skewness": 3.3804
        },
        {
          "timestamp": "2026-06-03T02:00:01.016574+00:00",
          "implied_mean": 0.219,
          "std_dev": 0.201,
          "skewness": 3.3804
        },
        {
          "timestamp": "2026-06-03T08:00:04.863048+00:00",
          "implied_mean": 0.222,
          "std_dev": 0.2007,
          "skewness": 3.3524
        },
        {
          "timestamp": "2026-06-03T14:00:02.931050+00:00",
          "implied_mean": 0.215,
          "std_dev": 0.1788,
          "skewness": 3.5583
        },
        {
          "timestamp": "2026-06-03T20:00:04.396391+00:00",
          "implied_mean": 0.214,
          "std_dev": 0.1783,
          "skewness": 3.5996
        },
        {
          "timestamp": "2026-06-04T02:00:05.558270+00:00",
          "implied_mean": 0.207,
          "std_dev": 0.1787,
          "skewness": 3.6886
        },
        {
          "timestamp": "2026-06-04T08:00:01.826168+00:00",
          "implied_mean": 0.216,
          "std_dev": 0.1753,
          "skewness": 3.7899
        },
        {
          "timestamp": "2026-06-04T14:00:04.825699+00:00",
          "implied_mean": 0.216,
          "std_dev": 0.1753,
          "skewness": 3.7899
        },
        {
          "timestamp": "2026-06-04T20:00:02.015947+00:00",
          "implied_mean": 0.218,
          "std_dev": 0.1751,
          "skewness": 3.7695
        },
        {
          "timestamp": "2026-06-05T02:00:05.139466+00:00",
          "implied_mean": 0.218,
          "std_dev": 0.1751,
          "skewness": 3.7695
        },
        {
          "timestamp": "2026-06-05T08:00:05.406934+00:00",
          "implied_mean": 0.211,
          "std_dev": 0.1785,
          "skewness": 3.6357
        },
        {
          "timestamp": "2026-06-05T14:00:05.529464+00:00",
          "implied_mean": 0.21,
          "std_dev": 0.1786,
          "skewness": 3.6484
        },
        {
          "timestamp": "2026-06-05T20:00:03.259677+00:00",
          "implied_mean": 0.21,
          "std_dev": 0.1786,
          "skewness": 3.6484
        },
        {
          "timestamp": "2026-06-06T02:00:02.750302+00:00",
          "implied_mean": 0.213,
          "std_dev": 0.179,
          "skewness": 3.5814
        },
        {
          "timestamp": "2026-06-06T08:00:05.063210+00:00",
          "implied_mean": 0.214,
          "std_dev": 0.1789,
          "skewness": 3.5697
        },
        {
          "timestamp": "2026-06-06T14:00:04.115414+00:00",
          "implied_mean": 0.214,
          "std_dev": 0.1789,
          "skewness": 3.5697
        },
        {
          "timestamp": "2026-06-06T20:00:05.989113+00:00",
          "implied_mean": 0.213,
          "std_dev": 0.1795,
          "skewness": 3.5416
        },
        {
          "timestamp": "2026-06-07T02:00:03.141352+00:00",
          "implied_mean": 0.212,
          "std_dev": 0.1796,
          "skewness": 3.5537
        },
        {
          "timestamp": "2026-06-07T08:00:04.590402+00:00",
          "implied_mean": 0.209,
          "std_dev": 0.1741,
          "skewness": 3.8042
        },
        {
          "timestamp": "2026-06-07T14:00:03.779191+00:00",
          "implied_mean": 0.21,
          "std_dev": 0.1741,
          "skewness": 3.791
        },
        {
          "timestamp": "2026-06-07T20:00:04.873686+00:00",
          "implied_mean": 0.217,
          "std_dev": 0.1758,
          "skewness": 3.581
        },
        {
          "timestamp": "2026-06-08T02:00:05.484895+00:00",
          "implied_mean": 0.215,
          "std_dev": 0.1754,
          "skewness": 3.634
        },
        {
          "timestamp": "2026-06-08T08:00:05.061809+00:00",
          "implied_mean": 0.215,
          "std_dev": 0.1754,
          "skewness": 3.634
        },
        {
          "timestamp": "2026-06-08T14:00:05.596057+00:00",
          "implied_mean": 0.215,
          "std_dev": 0.1737,
          "skewness": 3.7538
        },
        {
          "timestamp": "2026-06-08T20:00:05.493883+00:00",
          "implied_mean": 0.206,
          "std_dev": 0.176,
          "skewness": 3.7381
        },
        {
          "timestamp": "2026-06-09T02:00:06.083278+00:00",
          "implied_mean": 0.21,
          "std_dev": 0.1741,
          "skewness": 3.8024
        },
        {
          "timestamp": "2026-06-09T08:00:04.768805+00:00",
          "implied_mean": 0.224,
          "std_dev": 0.1767,
          "skewness": 3.4995
        },
        {
          "timestamp": "2026-06-09T14:00:04.970342+00:00",
          "implied_mean": 0.223,
          "std_dev": 0.1796,
          "skewness": 3.3497
        },
        {
          "timestamp": "2026-06-09T20:00:05.165364+00:00",
          "implied_mean": 0.209,
          "std_dev": 0.1753,
          "skewness": 3.7281
        },
        {
          "timestamp": "2026-06-10T02:00:05.357584+00:00",
          "implied_mean": 0.2,
          "std_dev": 0.1755,
          "skewness": 3.8628
        },
        {
          "timestamp": "2026-06-10T08:00:00.946087+00:00",
          "implied_mean": 0.203,
          "std_dev": 0.1749,
          "skewness": 3.8468
        },
        {
          "timestamp": "2026-06-10T14:00:05.466072+00:00",
          "implied_mean": 0.235,
          "std_dev": 0.1984,
          "skewness": 2.4523
        },
        {
          "timestamp": "2026-06-10T20:00:06.379219+00:00",
          "implied_mean": 0.237,
          "std_dev": 0.1971,
          "skewness": 2.4885
        },
        {
          "timestamp": "2026-06-11T02:00:05.752474+00:00",
          "implied_mean": 0.215,
          "std_dev": 0.1777,
          "skewness": 3.469
        },
        {
          "timestamp": "2026-06-11T08:00:06.014991+00:00",
          "implied_mean": 0.215,
          "std_dev": 0.1777,
          "skewness": 3.469
        },
        {
          "timestamp": "2026-06-11T14:00:06.181430+00:00",
          "implied_mean": 0.215,
          "std_dev": 0.1777,
          "skewness": 3.469
        },
        {
          "timestamp": "2026-06-11T20:00:04.232199+00:00",
          "implied_mean": 0.216,
          "std_dev": 0.1782,
          "skewness": 3.4287
        },
        {
          "timestamp": "2026-06-12T02:00:06.027300+00:00",
          "implied_mean": 0.234,
          "std_dev": 0.1638,
          "skewness": 4.2581
        },
        {
          "timestamp": "2026-06-12T08:00:06.232905+00:00",
          "implied_mean": 0.234,
          "std_dev": 0.1638,
          "skewness": 4.2581
        },
        {
          "timestamp": "2026-06-12T14:00:05.441161+00:00",
          "implied_mean": 0.234,
          "std_dev": 0.1638,
          "skewness": 4.2581
        },
        {
          "timestamp": "2026-06-12T20:00:01.621394+00:00",
          "implied_mean": 0.234,
          "std_dev": 0.1638,
          "skewness": 4.2581
        },
        {
          "timestamp": "2026-06-13T02:00:04.953326+00:00",
          "implied_mean": 0.179,
          "std_dev": 0.2111,
          "skewness": 2.0831
        },
        {
          "timestamp": "2026-06-13T08:00:06.062947+00:00",
          "implied_mean": 0.179,
          "std_dev": 0.2111,
          "skewness": 2.0831
        }
      ],
      "distribution": [
        {
          "label": "0.1%\u20130.2%",
          "strike": 0.1,
          "probability": 0.36,
          "yes_price": 0.82,
          "volume": 0
        },
        {
          "label": "0.2%\u20130.3%",
          "strike": 0.2,
          "probability": 0.27,
          "yes_price": 0.46,
          "volume": 0
        },
        {
          "label": "0.3%\u20130.4%",
          "strike": 0.3,
          "probability": 0.18,
          "yes_price": 0.19,
          "volume": 0
        }
      ],
      "label": "Core CPI (MoM)",
      "is_probability": false,
      "annotations": [
        {
          "event_date": "2026-06-10",
          "label": "CPI (May)",
          "type": "cpi",
          "notes": "",
          "is_past": true
        },
        {
          "event_date": "2026-07-14",
          "label": "CPI (Jun)",
          "type": "cpi",
          "notes": "",
          "is_past": false
        },
        {
          "event_date": "2026-08-12",
          "label": "CPI (Jul)",
          "type": "cpi",
          "notes": "",
          "is_past": false
        },
        {
          "event_date": "2026-09-11",
          "label": "CPI (Aug)",
          "type": "cpi",
          "notes": "",
          "is_past": false
        },
        {
          "event_date": "2026-10-14",
          "label": "CPI (Sep)",
          "type": "cpi",
          "notes": "",
          "is_past": false
        },
        {
          "event_date": "2026-11-10",
          "label": "CPI (Oct)",
          "type": "cpi",
          "notes": "",
          "is_past": false
        },
        {
          "event_date": "2026-12-10",
          "label": "CPI (Nov)",
          "type": "cpi",
          "notes": "",
          "is_past": false
        }
      ]
    },
    "GDP": {
      "contract_series": "KXGDP-26JUL30",
      "latest_run": "2026-06-13T08:00:06.062947+00:00",
      "implied_mean": 2.455,
      "std_dev": 1.1093,
      "skewness": -0.5589,
      "market_volume_usd": 91562.0,
      "days_to_event": 47,
      "trend": [
        {
          "timestamp": "2026-05-30T14:00:00.763285+00:00",
          "implied_mean": 2.62,
          "std_dev": 0.9858,
          "skewness": -0.3181
        },
        {
          "timestamp": "2026-05-30T20:00:00.612362+00:00",
          "implied_mean": 2.625,
          "std_dev": 0.9621,
          "skewness": -0.3432
        },
        {
          "timestamp": "2026-05-31T02:00:00.812212+00:00",
          "implied_mean": 2.645,
          "std_dev": 0.9799,
          "skewness": -0.3837
        },
        {
          "timestamp": "2026-05-31T08:00:00.964058+00:00",
          "implied_mean": 2.635,
          "std_dev": 0.9762,
          "skewness": -0.3621
        },
        {
          "timestamp": "2026-05-31T14:00:01.418772+00:00",
          "implied_mean": 2.6275,
          "std_dev": 1.0084,
          "skewness": -0.4019
        },
        {
          "timestamp": "2026-05-31T20:00:01.591951+00:00",
          "implied_mean": 2.5725,
          "std_dev": 1.0163,
          "skewness": -0.3199
        },
        {
          "timestamp": "2026-06-01T02:00:05.631255+00:00",
          "implied_mean": 2.5625,
          "std_dev": 1.0389,
          "skewness": -0.3838
        },
        {
          "timestamp": "2026-06-01T08:00:00.435070+00:00",
          "implied_mean": 2.5275,
          "std_dev": 1.0093,
          "skewness": -0.4056
        },
        {
          "timestamp": "2026-06-01T14:00:01.532592+00:00",
          "implied_mean": 2.5275,
          "std_dev": 1.0093,
          "skewness": -0.4056
        },
        {
          "timestamp": "2026-06-01T20:00:05.112607+00:00",
          "implied_mean": 2.5625,
          "std_dev": 1.0052,
          "skewness": -0.4644
        },
        {
          "timestamp": "2026-06-02T02:00:01.395096+00:00",
          "implied_mean": 2.555,
          "std_dev": 1.0085,
          "skewness": -0.3652
        },
        {
          "timestamp": "2026-06-02T08:00:01.384066+00:00",
          "implied_mean": 2.5575,
          "std_dev": 0.9974,
          "skewness": -0.3613
        },
        {
          "timestamp": "2026-06-02T14:00:01.758389+00:00",
          "implied_mean": 2.5375,
          "std_dev": 0.9813,
          "skewness": -0.3751
        },
        {
          "timestamp": "2026-06-02T20:00:04.326511+00:00",
          "implied_mean": 2.4725,
          "std_dev": 0.9688,
          "skewness": -0.1858
        },
        {
          "timestamp": "2026-06-03T02:00:01.016574+00:00",
          "implied_mean": 2.465,
          "std_dev": 1.066,
          "skewness": -0.5658
        },
        {
          "timestamp": "2026-06-03T08:00:04.863048+00:00",
          "implied_mean": 2.48,
          "std_dev": 1.0768,
          "skewness": -0.5399
        },
        {
          "timestamp": "2026-06-03T14:00:02.931050+00:00",
          "implied_mean": 2.52,
          "std_dev": 1.1021,
          "skewness": -0.5942
        },
        {
          "timestamp": "2026-06-03T20:00:04.396391+00:00",
          "implied_mean": 2.455,
          "std_dev": 1.0922,
          "skewness": -0.4109
        },
        {
          "timestamp": "2026-06-04T02:00:05.558270+00:00",
          "implied_mean": 2.435,
          "std_dev": 1.0396,
          "skewness": -0.2864
        },
        {
          "timestamp": "2026-06-04T08:00:01.826168+00:00",
          "implied_mean": 2.4275,
          "std_dev": 1.0382,
          "skewness": -0.2558
        },
        {
          "timestamp": "2026-06-04T14:00:04.825699+00:00",
          "implied_mean": 2.4475,
          "std_dev": 1.0077,
          "skewness": -0.2234
        },
        {
          "timestamp": "2026-06-04T20:00:02.015947+00:00",
          "implied_mean": 2.4575,
          "std_dev": 1.0155,
          "skewness": -0.2341
        },
        {
          "timestamp": "2026-06-05T02:00:05.139466+00:00",
          "implied_mean": 2.4125,
          "std_dev": 0.9113,
          "skewness": -0.4801
        },
        {
          "timestamp": "2026-06-05T08:00:05.406934+00:00",
          "implied_mean": 2.49,
          "std_dev": 1.0068,
          "skewness": -0.2372
        },
        {
          "timestamp": "2026-06-05T14:00:05.529464+00:00",
          "implied_mean": 2.49,
          "std_dev": 1.0068,
          "skewness": -0.2372
        },
        {
          "timestamp": "2026-06-05T20:00:03.259677+00:00",
          "implied_mean": 2.4575,
          "std_dev": 0.9605,
          "skewness": -0.3833
        },
        {
          "timestamp": "2026-06-06T02:00:02.750302+00:00",
          "implied_mean": 2.3625,
          "std_dev": 0.8975,
          "skewness": -0.3644
        },
        {
          "timestamp": "2026-06-06T08:00:05.063210+00:00",
          "implied_mean": 2.415,
          "std_dev": 0.9187,
          "skewness": -0.4805
        },
        {
          "timestamp": "2026-06-06T14:00:04.115414+00:00",
          "implied_mean": 2.405,
          "std_dev": 0.9123,
          "skewness": -0.413
        },
        {
          "timestamp": "2026-06-06T20:00:05.989113+00:00",
          "implied_mean": 2.43,
          "std_dev": 0.8896,
          "skewness": -0.4009
        },
        {
          "timestamp": "2026-06-07T02:00:03.141352+00:00",
          "implied_mean": 2.43,
          "std_dev": 0.8896,
          "skewness": -0.4009
        },
        {
          "timestamp": "2026-06-07T08:00:04.590402+00:00",
          "implied_mean": 2.49,
          "std_dev": 0.9598,
          "skewness": -0.2261
        },
        {
          "timestamp": "2026-06-07T14:00:03.779191+00:00",
          "implied_mean": 2.485,
          "std_dev": 0.9597,
          "skewness": -0.2108
        },
        {
          "timestamp": "2026-06-07T20:00:04.873686+00:00",
          "implied_mean": 2.49,
          "std_dev": 0.9572,
          "skewness": -0.2238
        },
        {
          "timestamp": "2026-06-08T02:00:05.484895+00:00",
          "implied_mean": 2.49,
          "std_dev": 0.936,
          "skewness": -0.0945
        },
        {
          "timestamp": "2026-06-08T08:00:05.061809+00:00",
          "implied_mean": 2.5125,
          "std_dev": 0.9456,
          "skewness": -0.1551
        },
        {
          "timestamp": "2026-06-08T14:00:05.596057+00:00",
          "implied_mean": 2.5375,
          "std_dev": 0.945,
          "skewness": -0.233
        },
        {
          "timestamp": "2026-06-08T20:00:05.493883+00:00",
          "implied_mean": 2.5175,
          "std_dev": 0.9456,
          "skewness": -0.1707
        },
        {
          "timestamp": "2026-06-09T02:00:06.083278+00:00",
          "implied_mean": 2.4625,
          "std_dev": 0.9633,
          "skewness": -0.042
        },
        {
          "timestamp": "2026-06-09T08:00:04.768805+00:00",
          "implied_mean": 2.4925,
          "std_dev": 1.0096,
          "skewness": -0.2305
        },
        {
          "timestamp": "2026-06-09T14:00:04.970342+00:00",
          "implied_mean": 2.4975,
          "std_dev": 1.0096,
          "skewness": -0.245
        },
        {
          "timestamp": "2026-06-09T20:00:05.165364+00:00",
          "implied_mean": 2.4625,
          "std_dev": 1.055,
          "skewness": -0.2858
        },
        {
          "timestamp": "2026-06-10T02:00:05.357584+00:00",
          "implied_mean": 2.4125,
          "std_dev": 0.9984,
          "skewness": -0.3571
        },
        {
          "timestamp": "2026-06-10T08:00:00.946087+00:00",
          "implied_mean": 2.4,
          "std_dev": 1.0012,
          "skewness": -0.2996
        },
        {
          "timestamp": "2026-06-10T14:00:05.466072+00:00",
          "implied_mean": 2.4,
          "std_dev": 1.0012,
          "skewness": -0.2996
        },
        {
          "timestamp": "2026-06-10T20:00:06.379219+00:00",
          "implied_mean": 2.455,
          "std_dev": 1.0298,
          "skewness": -0.3556
        },
        {
          "timestamp": "2026-06-11T02:00:05.752474+00:00",
          "implied_mean": 2.585,
          "std_dev": 0.9139,
          "skewness": -0.4841
        },
        {
          "timestamp": "2026-06-11T08:00:06.014991+00:00",
          "implied_mean": 2.565,
          "std_dev": 0.9504,
          "skewness": -0.3668
        },
        {
          "timestamp": "2026-06-11T14:00:06.181430+00:00",
          "implied_mean": 2.555,
          "std_dev": 0.9537,
          "skewness": -0.3379
        },
        {
          "timestamp": "2026-06-11T20:00:04.232199+00:00",
          "implied_mean": 2.39,
          "std_dev": 1.0632,
          "skewness": -0.2465
        },
        {
          "timestamp": "2026-06-12T02:00:06.027300+00:00",
          "implied_mean": 2.445,
          "std_dev": 1.0414,
          "skewness": -0.4554
        },
        {
          "timestamp": "2026-06-12T08:00:06.232905+00:00",
          "implied_mean": 2.445,
          "std_dev": 1.0975,
          "skewness": -0.5443
        },
        {
          "timestamp": "2026-06-12T14:00:05.441161+00:00",
          "implied_mean": 2.445,
          "std_dev": 1.0975,
          "skewness": -0.5443
        },
        {
          "timestamp": "2026-06-12T20:00:01.621394+00:00",
          "implied_mean": 2.47,
          "std_dev": 1.0985,
          "skewness": -0.6098
        },
        {
          "timestamp": "2026-06-13T02:00:04.953326+00:00",
          "implied_mean": 2.45,
          "std_dev": 1.1068,
          "skewness": -0.5526
        },
        {
          "timestamp": "2026-06-13T08:00:06.062947+00:00",
          "implied_mean": 2.455,
          "std_dev": 1.1093,
          "skewness": -0.5589
        }
      ],
      "distribution": [
        {
          "label": "2%\u20132.5%",
          "strike": 2.0,
          "probability": 0.22,
          "yes_price": 0.72,
          "volume": 0
        },
        {
          "label": "2.5%\u20133%",
          "strike": 2.5,
          "probability": 0.16,
          "yes_price": 0.5,
          "volume": 0
        },
        {
          "label": "3.5%\u20134%",
          "strike": 3.5,
          "probability": 0.14,
          "yes_price": 0.22,
          "volume": 0
        }
      ],
      "label": "GDP Growth",
      "is_probability": false,
      "annotations": [
        {
          "event_date": "2026-06-25",
          "label": "GDP Q1 2026 (3rd Est.)",
          "type": "gdp",
          "notes": "Third estimate",
          "is_past": false
        }
      ]
    },
    "Recession": {
      "contract_series": "KXNBERRECESSQ",
      "latest_run": "2026-06-13T08:00:06.062947+00:00",
      "implied_mean": 0.068,
      "std_dev": null,
      "skewness": null,
      "market_volume_usd": 504551.0,
      "days_to_event": 201,
      "trend": [
        {
          "timestamp": "2026-05-30T14:00:00.763285+00:00",
          "implied_mean": 0.046,
          "std_dev": null,
          "skewness": null
        },
        {
          "timestamp": "2026-05-30T20:00:00.612362+00:00",
          "implied_mean": 0.046,
          "std_dev": null,
          "skewness": null
        },
        {
          "timestamp": "2026-05-31T02:00:00.812212+00:00",
          "implied_mean": 0.046,
          "std_dev": null,
          "skewness": null
        },
        {
          "timestamp": "2026-05-31T08:00:00.964058+00:00",
          "implied_mean": 0.21,
          "std_dev": null,
          "skewness": null
        },
        {
          "timestamp": "2026-05-31T14:00:01.418772+00:00",
          "implied_mean": 0.21,
          "std_dev": null,
          "skewness": null
        },
        {
          "timestamp": "2026-05-31T20:00:01.591951+00:00",
          "implied_mean": 0.21,
          "std_dev": null,
          "skewness": null
        },
        {
          "timestamp": "2026-06-01T02:00:05.631255+00:00",
          "implied_mean": 0.21,
          "std_dev": null,
          "skewness": null
        },
        {
          "timestamp": "2026-06-01T08:00:00.435070+00:00",
          "implied_mean": 0.107,
          "std_dev": null,
          "skewness": null
        },
        {
          "timestamp": "2026-06-01T14:00:01.532592+00:00",
          "implied_mean": 0.107,
          "std_dev": null,
          "skewness": null
        },
        {
          "timestamp": "2026-06-01T20:00:05.112607+00:00",
          "implied_mean": 0.107,
          "std_dev": null,
          "skewness": null
        },
        {
          "timestamp": "2026-06-02T02:00:01.395096+00:00",
          "implied_mean": 0.107,
          "std_dev": null,
          "skewness": null
        },
        {
          "timestamp": "2026-06-02T08:00:01.384066+00:00",
          "implied_mean": 0.107,
          "std_dev": null,
          "skewness": null
        },
        {
          "timestamp": "2026-06-02T14:00:01.758389+00:00",
          "implied_mean": 0.107,
          "std_dev": null,
          "skewness": null
        },
        {
          "timestamp": "2026-06-02T20:00:04.326511+00:00",
          "implied_mean": 0.107,
          "std_dev": null,
          "skewness": null
        },
        {
          "timestamp": "2026-06-03T02:00:01.016574+00:00",
          "implied_mean": 0.107,
          "std_dev": null,
          "skewness": null
        },
        {
          "timestamp": "2026-06-03T08:00:04.863048+00:00",
          "implied_mean": 0.107,
          "std_dev": null,
          "skewness": null
        },
        {
          "timestamp": "2026-06-03T14:00:02.931050+00:00",
          "implied_mean": 0.107,
          "std_dev": null,
          "skewness": null
        },
        {
          "timestamp": "2026-06-03T20:00:04.396391+00:00",
          "implied_mean": 0.025,
          "std_dev": null,
          "skewness": null
        },
        {
          "timestamp": "2026-06-04T02:00:05.558270+00:00",
          "implied_mean": 0.025,
          "std_dev": null,
          "skewness": null
        },
        {
          "timestamp": "2026-06-04T08:00:01.826168+00:00",
          "implied_mean": 0.098,
          "std_dev": null,
          "skewness": null
        },
        {
          "timestamp": "2026-06-04T14:00:04.825699+00:00",
          "implied_mean": 0.098,
          "std_dev": null,
          "skewness": null
        },
        {
          "timestamp": "2026-06-04T20:00:02.015947+00:00",
          "implied_mean": 0.098,
          "std_dev": null,
          "skewness": null
        },
        {
          "timestamp": "2026-06-05T02:00:05.139466+00:00",
          "implied_mean": 0.098,
          "std_dev": null,
          "skewness": null
        },
        {
          "timestamp": "2026-06-05T08:00:05.406934+00:00",
          "implied_mean": 0.098,
          "std_dev": null,
          "skewness": null
        },
        {
          "timestamp": "2026-06-05T14:00:05.529464+00:00",
          "implied_mean": 0.098,
          "std_dev": null,
          "skewness": null
        },
        {
          "timestamp": "2026-06-05T20:00:03.259677+00:00",
          "implied_mean": 0.098,
          "std_dev": null,
          "skewness": null
        },
        {
          "timestamp": "2026-06-06T02:00:02.750302+00:00",
          "implied_mean": 0.098,
          "std_dev": null,
          "skewness": null
        },
        {
          "timestamp": "2026-06-06T08:00:05.063210+00:00",
          "implied_mean": 0.095,
          "std_dev": null,
          "skewness": null
        },
        {
          "timestamp": "2026-06-06T14:00:04.115414+00:00",
          "implied_mean": 0.095,
          "std_dev": null,
          "skewness": null
        },
        {
          "timestamp": "2026-06-06T20:00:05.989113+00:00",
          "implied_mean": 0.095,
          "std_dev": null,
          "skewness": null
        },
        {
          "timestamp": "2026-06-07T02:00:03.141352+00:00",
          "implied_mean": 0.095,
          "std_dev": null,
          "skewness": null
        },
        {
          "timestamp": "2026-06-07T08:00:04.590402+00:00",
          "implied_mean": 0.031,
          "std_dev": null,
          "skewness": null
        },
        {
          "timestamp": "2026-06-07T14:00:03.779191+00:00",
          "implied_mean": 0.031,
          "std_dev": null,
          "skewness": null
        },
        {
          "timestamp": "2026-06-07T20:00:04.873686+00:00",
          "implied_mean": 0.031,
          "std_dev": null,
          "skewness": null
        },
        {
          "timestamp": "2026-06-08T02:00:05.484895+00:00",
          "implied_mean": 0.03,
          "std_dev": null,
          "skewness": null
        },
        {
          "timestamp": "2026-06-08T08:00:05.061809+00:00",
          "implied_mean": 0.03,
          "std_dev": null,
          "skewness": null
        },
        {
          "timestamp": "2026-06-08T14:00:05.596057+00:00",
          "implied_mean": 0.03,
          "std_dev": null,
          "skewness": null
        },
        {
          "timestamp": "2026-06-08T20:00:05.493883+00:00",
          "implied_mean": 0.03,
          "std_dev": null,
          "skewness": null
        },
        {
          "timestamp": "2026-06-09T02:00:06.083278+00:00",
          "implied_mean": 0.03,
          "std_dev": null,
          "skewness": null
        },
        {
          "timestamp": "2026-06-09T08:00:04.768805+00:00",
          "implied_mean": 0.03,
          "std_dev": null,
          "skewness": null
        },
        {
          "timestamp": "2026-06-09T14:00:04.970342+00:00",
          "implied_mean": 0.03,
          "std_dev": null,
          "skewness": null
        },
        {
          "timestamp": "2026-06-09T20:00:05.165364+00:00",
          "implied_mean": 0.031,
          "std_dev": null,
          "skewness": null
        },
        {
          "timestamp": "2026-06-10T02:00:05.357584+00:00",
          "implied_mean": 0.031,
          "std_dev": null,
          "skewness": null
        },
        {
          "timestamp": "2026-06-10T08:00:00.946087+00:00",
          "implied_mean": 0.031,
          "std_dev": null,
          "skewness": null
        },
        {
          "timestamp": "2026-06-10T14:00:05.466072+00:00",
          "implied_mean": 0.031,
          "std_dev": null,
          "skewness": null
        },
        {
          "timestamp": "2026-06-10T20:00:06.379219+00:00",
          "implied_mean": 0.031,
          "std_dev": null,
          "skewness": null
        },
        {
          "timestamp": "2026-06-11T02:00:05.752474+00:00",
          "implied_mean": 0.031,
          "std_dev": null,
          "skewness": null
        },
        {
          "timestamp": "2026-06-11T08:00:06.014991+00:00",
          "implied_mean": 0.031,
          "std_dev": null,
          "skewness": null
        },
        {
          "timestamp": "2026-06-11T14:00:06.181430+00:00",
          "implied_mean": 0.031,
          "std_dev": null,
          "skewness": null
        },
        {
          "timestamp": "2026-06-11T20:00:04.232199+00:00",
          "implied_mean": 0.031,
          "std_dev": null,
          "skewness": null
        },
        {
          "timestamp": "2026-06-12T02:00:06.027300+00:00",
          "implied_mean": 0.031,
          "std_dev": null,
          "skewness": null
        },
        {
          "timestamp": "2026-06-12T08:00:06.232905+00:00",
          "implied_mean": 0.031,
          "std_dev": null,
          "skewness": null
        },
        {
          "timestamp": "2026-06-12T14:00:05.441161+00:00",
          "implied_mean": 0.031,
          "std_dev": null,
          "skewness": null
        },
        {
          "timestamp": "2026-06-12T20:00:01.621394+00:00",
          "implied_mean": 0.069,
          "std_dev": null,
          "skewness": null
        },
        {
          "timestamp": "2026-06-13T02:00:04.953326+00:00",
          "implied_mean": 0.068,
          "std_dev": null,
          "skewness": null
        },
        {
          "timestamp": "2026-06-13T08:00:06.062947+00:00",
          "implied_mean": 0.068,
          "std_dev": null,
          "skewness": null
        }
      ],
      "distribution": [],
      "label": "Recession Probability",
      "is_probability": true,
      "annotations": []
    },
    "FF_Rate": {
      "label": "Fed Funds Rate",
      "is_probability": true,
      "meetings": [
        {
          "contract_series": "KXFEDDECISION-26JUN",
          "latest_run": "2026-06-13T08:00:06.062947+00:00",
          "implied_mean": 0.98,
          "std_dev": null,
          "skewness": null,
          "market_volume_usd": 22598336.0,
          "days_to_event": 4,
          "trend": [
            {
              "timestamp": "2026-05-30T14:00:00.763285+00:00",
              "implied_mean": 0.97,
              "std_dev": null,
              "skewness": null
            },
            {
              "timestamp": "2026-05-30T20:00:00.612362+00:00",
              "implied_mean": 0.96,
              "std_dev": null,
              "skewness": null
            },
            {
              "timestamp": "2026-05-31T02:00:00.812212+00:00",
              "implied_mean": 0.97,
              "std_dev": null,
              "skewness": null
            },
            {
              "timestamp": "2026-05-31T08:00:00.964058+00:00",
              "implied_mean": 0.96,
              "std_dev": null,
              "skewness": null
            },
            {
              "timestamp": "2026-05-31T14:00:01.418772+00:00",
              "implied_mean": 0.96,
              "std_dev": null,
              "skewness": null
            },
            {
              "timestamp": "2026-05-31T20:00:01.591951+00:00",
              "implied_mean": 0.97,
              "std_dev": null,
              "skewness": null
            },
            {
              "timestamp": "2026-06-01T02:00:05.631255+00:00",
              "implied_mean": 0.97,
              "std_dev": null,
              "skewness": null
            },
            {
              "timestamp": "2026-06-01T08:00:00.435070+00:00",
              "implied_mean": 0.96,
              "std_dev": null,
              "skewness": null
            },
            {
              "timestamp": "2026-06-01T14:00:01.532592+00:00",
              "implied_mean": 0.97,
              "std_dev": null,
              "skewness": null
            },
            {
              "timestamp": "2026-06-01T20:00:05.112607+00:00",
              "implied_mean": 0.96,
              "std_dev": null,
              "skewness": null
            },
            {
              "timestamp": "2026-06-02T02:00:01.395096+00:00",
              "implied_mean": 0.96,
              "std_dev": null,
              "skewness": null
            },
            {
              "timestamp": "2026-06-02T08:00:01.384066+00:00",
              "implied_mean": 0.97,
              "std_dev": null,
              "skewness": null
            },
            {
              "timestamp": "2026-06-02T14:00:01.758389+00:00",
              "implied_mean": 0.96,
              "std_dev": null,
              "skewness": null
            },
            {
              "timestamp": "2026-06-02T20:00:04.326511+00:00",
              "implied_mean": 0.96,
              "std_dev": null,
              "skewness": null
            },
            {
              "timestamp": "2026-06-03T02:00:01.016574+00:00",
              "implied_mean": 0.97,
              "std_dev": null,
              "skewness": null
            },
            {
              "timestamp": "2026-06-03T08:00:04.863048+00:00",
              "implied_mean": 0.97,
              "std_dev": null,
              "skewness": null
            },
            {
              "timestamp": "2026-06-03T14:00:02.931050+00:00",
              "implied_mean": 0.96,
              "std_dev": null,
              "skewness": null
            },
            {
              "timestamp": "2026-06-03T20:00:04.396391+00:00",
              "implied_mean": 0.96,
              "std_dev": null,
              "skewness": null
            },
            {
              "timestamp": "2026-06-04T02:00:05.558270+00:00",
              "implied_mean": 0.96,
              "std_dev": null,
              "skewness": null
            },
            {
              "timestamp": "2026-06-04T08:00:01.826168+00:00",
              "implied_mean": 0.97,
              "std_dev": null,
              "skewness": null
            },
            {
              "timestamp": "2026-06-04T14:00:04.825699+00:00",
              "implied_mean": 0.97,
              "std_dev": null,
              "skewness": null
            },
            {
              "timestamp": "2026-06-04T20:00:02.015947+00:00",
              "implied_mean": 0.96,
              "std_dev": null,
              "skewness": null
            },
            {
              "timestamp": "2026-06-05T02:00:05.139466+00:00",
              "implied_mean": 0.96,
              "std_dev": null,
              "skewness": null
            },
            {
              "timestamp": "2026-06-05T08:00:05.406934+00:00",
              "implied_mean": 0.97,
              "std_dev": null,
              "skewness": null
            },
            {
              "timestamp": "2026-06-05T14:00:05.529464+00:00",
              "implied_mean": 0.97,
              "std_dev": null,
              "skewness": null
            },
            {
              "timestamp": "2026-06-05T20:00:03.259677+00:00",
              "implied_mean": 0.98,
              "std_dev": null,
              "skewness": null
            },
            {
              "timestamp": "2026-06-06T02:00:02.750302+00:00",
              "implied_mean": 0.98,
              "std_dev": null,
              "skewness": null
            },
            {
              "timestamp": "2026-06-06T08:00:05.063210+00:00",
              "implied_mean": 0.97,
              "std_dev": null,
              "skewness": null
            },
            {
              "timestamp": "2026-06-06T14:00:04.115414+00:00",
              "implied_mean": 0.98,
              "std_dev": null,
              "skewness": null
            },
            {
              "timestamp": "2026-06-06T20:00:05.989113+00:00",
              "implied_mean": 0.97,
              "std_dev": null,
              "skewness": null
            },
            {
              "timestamp": "2026-06-07T02:00:03.141352+00:00",
              "implied_mean": 0.97,
              "std_dev": null,
              "skewness": null
            },
            {
              "timestamp": "2026-06-07T08:00:04.590402+00:00",
              "implied_mean": 0.97,
              "std_dev": null,
              "skewness": null
            },
            {
              "timestamp": "2026-06-07T14:00:03.779191+00:00",
              "implied_mean": 0.97,
              "std_dev": null,
              "skewness": null
            },
            {
              "timestamp": "2026-06-07T20:00:04.873686+00:00",
              "implied_mean": 0.98,
              "std_dev": null,
              "skewness": null
            },
            {
              "timestamp": "2026-06-08T02:00:05.484895+00:00",
              "implied_mean": 0.98,
              "std_dev": null,
              "skewness": null
            },
            {
              "timestamp": "2026-06-08T08:00:05.061809+00:00",
              "implied_mean": 0.98,
              "std_dev": null,
              "skewness": null
            },
            {
              "timestamp": "2026-06-08T14:00:05.596057+00:00",
              "implied_mean": 0.98,
              "std_dev": null,
              "skewness": null
            },
            {
              "timestamp": "2026-06-08T20:00:05.493883+00:00",
              "implied_mean": 0.98,
              "std_dev": null,
              "skewness": null
            },
            {
              "timestamp": "2026-06-09T02:00:06.083278+00:00",
              "implied_mean": 0.98,
              "std_dev": null,
              "skewness": null
            },
            {
              "timestamp": "2026-06-09T08:00:04.768805+00:00",
              "implied_mean": 0.98,
              "std_dev": null,
              "skewness": null
            },
            {
              "timestamp": "2026-06-09T14:00:04.970342+00:00",
              "implied_mean": 0.98,
              "std_dev": null,
              "skewness": null
            },
            {
              "timestamp": "2026-06-09T20:00:05.165364+00:00",
              "implied_mean": 0.98,
              "std_dev": null,
              "skewness": null
            },
            {
              "timestamp": "2026-06-10T02:00:05.357584+00:00",
              "implied_mean": 0.98,
              "std_dev": null,
              "skewness": null
            },
            {
              "timestamp": "2026-06-10T08:00:00.946087+00:00",
              "implied_mean": 0.98,
              "std_dev": null,
              "skewness": null
            },
            {
              "timestamp": "2026-06-10T14:00:05.466072+00:00",
              "implied_mean": 0.98,
              "std_dev": null,
              "skewness": null
            },
            {
              "timestamp": "2026-06-10T20:00:06.379219+00:00",
              "implied_mean": 0.98,
              "std_dev": null,
              "skewness": null
            },
            {
              "timestamp": "2026-06-11T02:00:05.752474+00:00",
              "implied_mean": 0.99,
              "std_dev": null,
              "skewness": null
            },
            {
              "timestamp": "2026-06-11T08:00:06.014991+00:00",
              "implied_mean": 0.99,
              "std_dev": null,
              "skewness": null
            },
            {
              "timestamp": "2026-06-11T14:00:06.181430+00:00",
              "implied_mean": 0.99,
              "std_dev": null,
              "skewness": null
            },
            {
              "timestamp": "2026-06-11T20:00:04.232199+00:00",
              "implied_mean": 0.98,
              "std_dev": null,
              "skewness": null
            },
            {
              "timestamp": "2026-06-12T02:00:06.027300+00:00",
              "implied_mean": 0.98,
              "std_dev": null,
              "skewness": null
            },
            {
              "timestamp": "2026-06-12T08:00:06.232905+00:00",
              "implied_mean": 0.98,
              "std_dev": null,
              "skewness": null
            },
            {
              "timestamp": "2026-06-12T14:00:05.441161+00:00",
              "implied_mean": 0.98,
              "std_dev": null,
              "skewness": null
            },
            {
              "timestamp": "2026-06-12T20:00:01.621394+00:00",
              "implied_mean": 0.98,
              "std_dev": null,
              "skewness": null
            },
            {
              "timestamp": "2026-06-13T02:00:04.953326+00:00",
              "implied_mean": 0.98,
              "std_dev": null,
              "skewness": null
            },
            {
              "timestamp": "2026-06-13T08:00:06.062947+00:00",
              "implied_mean": 0.98,
              "std_dev": null,
              "skewness": null
            }
          ],
          "distribution": [
            {
              "label": "Fed maintains rate",
              "strike": null,
              "probability": 0.98,
              "yes_price": 0.98,
              "volume": 0
            },
            {
              "label": "Cut >25bps",
              "strike": null,
              "probability": 0.01,
              "yes_price": 0.01,
              "volume": 0
            },
            {
              "label": "Cut 25bps",
              "strike": null,
              "probability": 0.01,
              "yes_price": 0.01,
              "volume": 0
            }
          ]
        },
        {
          "contract_series": "KXFEDDECISION-26JUL",
          "latest_run": "2026-06-13T08:00:06.062947+00:00",
          "implied_mean": 0.9,
          "std_dev": null,
          "skewness": null,
          "market_volume_usd": 938738.0,
          "days_to_event": 46,
          "trend": [
            {
              "timestamp": "2026-05-30T14:00:00.763285+00:00",
              "implied_mean": 0.91,
              "std_dev": null,
              "skewness": null
            },
            {
              "timestamp": "2026-05-30T20:00:00.612362+00:00",
              "implied_mean": 0.91,
              "std_dev": null,
              "skewness": null
            },
            {
              "timestamp": "2026-05-31T02:00:00.812212+00:00",
              "implied_mean": 0.9,
              "std_dev": null,
              "skewness": null
            },
            {
              "timestamp": "2026-05-31T08:00:00.964058+00:00",
              "implied_mean": 0.9,
              "std_dev": null,
              "skewness": null
            },
            {
              "timestamp": "2026-05-31T14:00:01.418772+00:00",
              "implied_mean": 0.9,
              "std_dev": null,
              "skewness": null
            },
            {
              "timestamp": "2026-05-31T20:00:01.591951+00:00",
              "implied_mean": 0.9,
              "std_dev": null,
              "skewness": null
            },
            {
              "timestamp": "2026-06-01T02:00:05.631255+00:00",
              "implied_mean": 0.87,
              "std_dev": null,
              "skewness": null
            },
            {
              "timestamp": "2026-06-01T08:00:00.435070+00:00",
              "implied_mean": 0.87,
              "std_dev": null,
              "skewness": null
            },
            {
              "timestamp": "2026-06-01T14:00:01.532592+00:00",
              "implied_mean": 0.9,
              "std_dev": null,
              "skewness": null
            },
            {
              "timestamp": "2026-06-01T20:00:05.112607+00:00",
              "implied_mean": 0.9,
              "std_dev": null,
              "skewness": null
            },
            {
              "timestamp": "2026-06-02T02:00:01.395096+00:00",
              "implied_mean": 0.9,
              "std_dev": null,
              "skewness": null
            },
            {
              "timestamp": "2026-06-02T08:00:01.384066+00:00",
              "implied_mean": 0.9,
              "std_dev": null,
              "skewness": null
            },
            {
              "timestamp": "2026-06-02T14:00:01.758389+00:00",
              "implied_mean": 0.9,
              "std_dev": null,
              "skewness": null
            },
            {
              "timestamp": "2026-06-02T20:00:04.326511+00:00",
              "implied_mean": 0.88,
              "std_dev": null,
              "skewness": null
            },
            {
              "timestamp": "2026-06-03T02:00:01.016574+00:00",
              "implied_mean": 0.91,
              "std_dev": null,
              "skewness": null
            },
            {
              "timestamp": "2026-06-03T08:00:04.863048+00:00",
              "implied_mean": 0.88,
              "std_dev": null,
              "skewness": null
            },
            {
              "timestamp": "2026-06-03T14:00:02.931050+00:00",
              "implied_mean": 0.89,
              "std_dev": null,
              "skewness": null
            },
            {
              "timestamp": "2026-06-03T20:00:04.396391+00:00",
              "implied_mean": 0.91,
              "std_dev": null,
              "skewness": null
            },
            {
              "timestamp": "2026-06-04T02:00:05.558270+00:00",
              "implied_mean": 0.91,
              "std_dev": null,
              "skewness": null
            },
            {
              "timestamp": "2026-06-04T08:00:01.826168+00:00",
              "implied_mean": 0.91,
              "std_dev": null,
              "skewness": null
            },
            {
              "timestamp": "2026-06-04T14:00:04.825699+00:00",
              "implied_mean": 0.91,
              "std_dev": null,
              "skewness": null
            },
            {
              "timestamp": "2026-06-04T20:00:02.015947+00:00",
              "implied_mean": 0.9,
              "std_dev": null,
              "skewness": null
            },
            {
              "timestamp": "2026-06-05T02:00:05.139466+00:00",
              "implied_mean": 0.9,
              "std_dev": null,
              "skewness": null
            },
            {
              "timestamp": "2026-06-05T08:00:05.406934+00:00",
              "implied_mean": 0.9,
              "std_dev": null,
              "skewness": null
            },
            {
              "timestamp": "2026-06-05T14:00:05.529464+00:00",
              "implied_mean": 0.91,
              "std_dev": null,
              "skewness": null
            },
            {
              "timestamp": "2026-06-05T20:00:03.259677+00:00",
              "implied_mean": 0.9,
              "std_dev": null,
              "skewness": null
            },
            {
              "timestamp": "2026-06-06T02:00:02.750302+00:00",
              "implied_mean": 0.9,
              "std_dev": null,
              "skewness": null
            },
            {
              "timestamp": "2026-06-06T08:00:05.063210+00:00",
              "implied_mean": 0.9,
              "std_dev": null,
              "skewness": null
            },
            {
              "timestamp": "2026-06-06T14:00:04.115414+00:00",
              "implied_mean": 0.92,
              "std_dev": null,
              "skewness": null
            },
            {
              "timestamp": "2026-06-06T20:00:05.989113+00:00",
              "implied_mean": 0.92,
              "std_dev": null,
              "skewness": null
            },
            {
              "timestamp": "2026-06-07T02:00:03.141352+00:00",
              "implied_mean": 0.92,
              "std_dev": null,
              "skewness": null
            },
            {
              "timestamp": "2026-06-07T08:00:04.590402+00:00",
              "implied_mean": 0.92,
              "std_dev": null,
              "skewness": null
            },
            {
              "timestamp": "2026-06-07T14:00:03.779191+00:00",
              "implied_mean": 0.92,
              "std_dev": null,
              "skewness": null
            },
            {
              "timestamp": "2026-06-07T20:00:04.873686+00:00",
              "implied_mean": 0.92,
              "std_dev": null,
              "skewness": null
            },
            {
              "timestamp": "2026-06-08T02:00:05.484895+00:00",
              "implied_mean": 0.88,
              "std_dev": null,
              "skewness": null
            },
            {
              "timestamp": "2026-06-08T08:00:05.061809+00:00",
              "implied_mean": 0.88,
              "std_dev": null,
              "skewness": null
            },
            {
              "timestamp": "2026-06-08T14:00:05.596057+00:00",
              "implied_mean": 0.92,
              "std_dev": null,
              "skewness": null
            },
            {
              "timestamp": "2026-06-08T20:00:05.493883+00:00",
              "implied_mean": 0.91,
              "std_dev": null,
              "skewness": null
            },
            {
              "timestamp": "2026-06-09T02:00:06.083278+00:00",
              "implied_mean": 0.93,
              "std_dev": null,
              "skewness": null
            },
            {
              "timestamp": "2026-06-09T08:00:04.768805+00:00",
              "implied_mean": 0.93,
              "std_dev": null,
              "skewness": null
            },
            {
              "timestamp": "2026-06-09T14:00:04.970342+00:00",
              "implied_mean": 0.91,
              "std_dev": null,
              "skewness": null
            },
            {
              "timestamp": "2026-06-09T20:00:05.165364+00:00",
              "implied_mean": 0.91,
              "std_dev": null,
              "skewness": null
            },
            {
              "timestamp": "2026-06-10T02:00:05.357584+00:00",
              "implied_mean": 0.92,
              "std_dev": null,
              "skewness": null
            },
            {
              "timestamp": "2026-06-10T08:00:00.946087+00:00",
              "implied_mean": 0.92,
              "std_dev": null,
              "skewness": null
            },
            {
              "timestamp": "2026-06-10T14:00:05.466072+00:00",
              "implied_mean": 0.92,
              "std_dev": null,
              "skewness": null
            },
            {
              "timestamp": "2026-06-10T20:00:06.379219+00:00",
              "implied_mean": 0.93,
              "std_dev": null,
              "skewness": null
            },
            {
              "timestamp": "2026-06-11T02:00:05.752474+00:00",
              "implied_mean": 0.92,
              "std_dev": null,
              "skewness": null
            },
            {
              "timestamp": "2026-06-11T08:00:06.014991+00:00",
              "implied_mean": 0.92,
              "std_dev": null,
              "skewness": null
            },
            {
              "timestamp": "2026-06-11T14:00:06.181430+00:00",
              "implied_mean": 0.92,
              "std_dev": null,
              "skewness": null
            },
            {
              "timestamp": "2026-06-11T20:00:04.232199+00:00",
              "implied_mean": 0.91,
              "std_dev": null,
              "skewness": null
            },
            {
              "timestamp": "2026-06-12T02:00:06.027300+00:00",
              "implied_mean": 0.89,
              "std_dev": null,
              "skewness": null
            },
            {
              "timestamp": "2026-06-12T08:00:06.232905+00:00",
              "implied_mean": 0.9,
              "std_dev": null,
              "skewness": null
            },
            {
              "timestamp": "2026-06-12T14:00:05.441161+00:00",
              "implied_mean": 0.92,
              "std_dev": null,
              "skewness": null
            },
            {
              "timestamp": "2026-06-12T20:00:01.621394+00:00",
              "implied_mean": 0.91,
              "std_dev": null,
              "skewness": null
            },
            {
              "timestamp": "2026-06-13T02:00:04.953326+00:00",
              "implied_mean": 0.92,
              "std_dev": null,
              "skewness": null
            },
            {
              "timestamp": "2026-06-13T08:00:06.062947+00:00",
              "implied_mean": 0.9,
              "std_dev": null,
              "skewness": null
            }
          ],
          "distribution": [
            {
              "label": "Fed maintains rate",
              "strike": null,
              "probability": 0.9,
              "yes_price": 0.9,
              "volume": 0
            },
            {
              "label": "Hike 25bps",
              "strike": null,
              "probability": 0.06,
              "yes_price": 0.06,
              "volume": 0
            },
            {
              "label": "Cut 25bps",
              "strike": null,
              "probability": 0.04,
              "yes_price": 0.04,
              "volume": 0
            }
          ]
        },
        {
          "contract_series": "KXFEDDECISION-26SEP",
          "latest_run": "2026-06-13T08:00:06.062947+00:00",
          "implied_mean": 0.79,
          "std_dev": null,
          "skewness": null,
          "market_volume_usd": 41393.0,
          "days_to_event": 95,
          "trend": [
            {
              "timestamp": "2026-05-30T14:00:00.763285+00:00",
              "implied_mean": 0.78,
              "std_dev": null,
              "skewness": null
            },
            {
              "timestamp": "2026-05-30T20:00:00.612362+00:00",
              "implied_mean": 0.78,
              "std_dev": null,
              "skewness": null
            },
            {
              "timestamp": "2026-05-31T02:00:00.812212+00:00",
              "implied_mean": 0.74,
              "std_dev": null,
              "skewness": null
            },
            {
              "timestamp": "2026-05-31T08:00:00.964058+00:00",
              "implied_mean": 0.74,
              "std_dev": null,
              "skewness": null
            },
            {
              "timestamp": "2026-05-31T14:00:01.418772+00:00",
              "implied_mean": 0.74,
              "std_dev": null,
              "skewness": null
            },
            {
              "timestamp": "2026-05-31T20:00:01.591951+00:00",
              "implied_mean": 0.74,
              "std_dev": null,
              "skewness": null
            },
            {
              "timestamp": "2026-06-01T02:00:05.631255+00:00",
              "implied_mean": 0.74,
              "std_dev": null,
              "skewness": null
            },
            {
              "timestamp": "2026-06-01T08:00:00.435070+00:00",
              "implied_mean": 0.74,
              "std_dev": null,
              "skewness": null
            },
            {
              "timestamp": "2026-06-01T14:00:01.532592+00:00",
              "implied_mean": 0.74,
              "std_dev": null,
              "skewness": null
            },
            {
              "timestamp": "2026-06-01T20:00:05.112607+00:00",
              "implied_mean": 0.74,
              "std_dev": null,
              "skewness": null
            },
            {
              "timestamp": "2026-06-02T02:00:01.395096+00:00",
              "implied_mean": 0.74,
              "std_dev": null,
              "skewness": null
            },
            {
              "timestamp": "2026-06-02T08:00:01.384066+00:00",
              "implied_mean": 0.74,
              "std_dev": null,
              "skewness": null
            },
            {
              "timestamp": "2026-06-02T14:00:01.758389+00:00",
              "implied_mean": 0.74,
              "std_dev": null,
              "skewness": null
            },
            {
              "timestamp": "2026-06-02T20:00:04.326511+00:00",
              "implied_mean": 0.81,
              "std_dev": null,
              "skewness": null
            },
            {
              "timestamp": "2026-06-03T02:00:01.016574+00:00",
              "implied_mean": 0.81,
              "std_dev": null,
              "skewness": null
            },
            {
              "timestamp": "2026-06-03T08:00:04.863048+00:00",
              "implied_mean": 0.81,
              "std_dev": null,
              "skewness": null
            },
            {
              "timestamp": "2026-06-03T14:00:02.931050+00:00",
              "implied_mean": 0.81,
              "std_dev": null,
              "skewness": null
            },
            {
              "timestamp": "2026-06-03T20:00:04.396391+00:00",
              "implied_mean": 0.81,
              "std_dev": null,
              "skewness": null
            },
            {
              "timestamp": "2026-06-04T02:00:05.558270+00:00",
              "implied_mean": 0.81,
              "std_dev": null,
              "skewness": null
            },
            {
              "timestamp": "2026-06-04T08:00:01.826168+00:00",
              "implied_mean": 0.81,
              "std_dev": null,
              "skewness": null
            },
            {
              "timestamp": "2026-06-04T14:00:04.825699+00:00",
              "implied_mean": 0.81,
              "std_dev": null,
              "skewness": null
            },
            {
              "timestamp": "2026-06-04T20:00:02.015947+00:00",
              "implied_mean": 0.81,
              "std_dev": null,
              "skewness": null
            },
            {
              "timestamp": "2026-06-05T02:00:05.139466+00:00",
              "implied_mean": 0.81,
              "std_dev": null,
              "skewness": null
            },
            {
              "timestamp": "2026-06-05T08:00:05.406934+00:00",
              "implied_mean": 0.81,
              "std_dev": null,
              "skewness": null
            },
            {
              "timestamp": "2026-06-05T14:00:05.529464+00:00",
              "implied_mean": 0.81,
              "std_dev": null,
              "skewness": null
            },
            {
              "timestamp": "2026-06-05T20:00:03.259677+00:00",
              "implied_mean": 0.81,
              "std_dev": null,
              "skewness": null
            },
            {
              "timestamp": "2026-06-06T02:00:02.750302+00:00",
              "implied_mean": 0.81,
              "std_dev": null,
              "skewness": null
            },
            {
              "timestamp": "2026-06-06T08:00:05.063210+00:00",
              "implied_mean": 0.76,
              "std_dev": null,
              "skewness": null
            },
            {
              "timestamp": "2026-06-06T14:00:04.115414+00:00",
              "implied_mean": 0.78,
              "std_dev": null,
              "skewness": null
            },
            {
              "timestamp": "2026-06-06T20:00:05.989113+00:00",
              "implied_mean": 0.78,
              "std_dev": null,
              "skewness": null
            },
            {
              "timestamp": "2026-06-07T02:00:03.141352+00:00",
              "implied_mean": 0.78,
              "std_dev": null,
              "skewness": null
            },
            {
              "timestamp": "2026-06-07T08:00:04.590402+00:00",
              "implied_mean": 0.78,
              "std_dev": null,
              "skewness": null
            },
            {
              "timestamp": "2026-06-07T14:00:03.779191+00:00",
              "implied_mean": 0.78,
              "std_dev": null,
              "skewness": null
            },
            {
              "timestamp": "2026-06-07T20:00:04.873686+00:00",
              "implied_mean": 0.78,
              "std_dev": null,
              "skewness": null
            },
            {
              "timestamp": "2026-06-08T02:00:05.484895+00:00",
              "implied_mean": 0.78,
              "std_dev": null,
              "skewness": null
            },
            {
              "timestamp": "2026-06-08T08:00:05.061809+00:00",
              "implied_mean": 0.78,
              "std_dev": null,
              "skewness": null
            },
            {
              "timestamp": "2026-06-08T14:00:05.596057+00:00",
              "implied_mean": 0.78,
              "std_dev": null,
              "skewness": null
            },
            {
              "timestamp": "2026-06-08T20:00:05.493883+00:00",
              "implied_mean": 0.8,
              "std_dev": null,
              "skewness": null
            },
            {
              "timestamp": "2026-06-09T02:00:06.083278+00:00",
              "implied_mean": 0.8,
              "std_dev": null,
              "skewness": null
            },
            {
              "timestamp": "2026-06-09T08:00:04.768805+00:00",
              "implied_mean": 0.8,
              "std_dev": null,
              "skewness": null
            },
            {
              "timestamp": "2026-06-09T14:00:04.970342+00:00",
              "implied_mean": 0.77,
              "std_dev": null,
              "skewness": null
            },
            {
              "timestamp": "2026-06-09T20:00:05.165364+00:00",
              "implied_mean": 0.77,
              "std_dev": null,
              "skewness": null
            },
            {
              "timestamp": "2026-06-10T02:00:05.357584+00:00",
              "implied_mean": 0.78,
              "std_dev": null,
              "skewness": null
            },
            {
              "timestamp": "2026-06-10T08:00:00.946087+00:00",
              "implied_mean": 0.78,
              "std_dev": null,
              "skewness": null
            },
            {
              "timestamp": "2026-06-10T14:00:05.466072+00:00",
              "implied_mean": 0.76,
              "std_dev": null,
              "skewness": null
            },
            {
              "timestamp": "2026-06-10T20:00:06.379219+00:00",
              "implied_mean": 0.76,
              "std_dev": null,
              "skewness": null
            },
            {
              "timestamp": "2026-06-11T02:00:05.752474+00:00",
              "implied_mean": 0.79,
              "std_dev": null,
              "skewness": null
            },
            {
              "timestamp": "2026-06-11T08:00:06.014991+00:00",
              "implied_mean": 0.76,
              "std_dev": null,
              "skewness": null
            },
            {
              "timestamp": "2026-06-11T14:00:06.181430+00:00",
              "implied_mean": 0.76,
              "std_dev": null,
              "skewness": null
            },
            {
              "timestamp": "2026-06-11T20:00:04.232199+00:00",
              "implied_mean": 0.8,
              "std_dev": null,
              "skewness": null
            },
            {
              "timestamp": "2026-06-12T02:00:06.027300+00:00",
              "implied_mean": 0.8,
              "std_dev": null,
              "skewness": null
            },
            {
              "timestamp": "2026-06-12T08:00:06.232905+00:00",
              "implied_mean": 0.76,
              "std_dev": null,
              "skewness": null
            },
            {
              "timestamp": "2026-06-12T14:00:05.441161+00:00",
              "implied_mean": 0.76,
              "std_dev": null,
              "skewness": null
            },
            {
              "timestamp": "2026-06-12T20:00:01.621394+00:00",
              "implied_mean": 0.76,
              "std_dev": null,
              "skewness": null
            },
            {
              "timestamp": "2026-06-13T02:00:04.953326+00:00",
              "implied_mean": 0.76,
              "std_dev": null,
              "skewness": null
            },
            {
              "timestamp": "2026-06-13T08:00:06.062947+00:00",
              "implied_mean": 0.79,
              "std_dev": null,
              "skewness": null
            }
          ],
          "distribution": [
            {
              "label": "Fed maintains rate",
              "strike": null,
              "probability": 0.79,
              "yes_price": 0.79,
              "volume": 0
            },
            {
              "label": "Hike 25bps",
              "strike": null,
              "probability": 0.2,
              "yes_price": 0.2,
              "volume": 0
            },
            {
              "label": "Cut 25bps",
              "strike": null,
              "probability": 0.06,
              "yes_price": 0.06,
              "volume": 0
            }
          ]
        }
      ],
      "annotations": [
        {
          "event_date": "2026-06-17",
          "label": "FOMC (Jun)",
          "type": "fomc",
          "notes": "",
          "is_past": false
        },
        {
          "event_date": "2026-07-29",
          "label": "FOMC (Jul)",
          "type": "fomc",
          "notes": "",
          "is_past": false
        },
        {
          "event_date": "2026-09-16",
          "label": "FOMC (Sep)",
          "type": "fomc",
          "notes": "",
          "is_past": false
        },
        {
          "event_date": "2026-10-28",
          "label": "FOMC (Oct)",
          "type": "fomc",
          "notes": "",
          "is_past": false
        },
        {
          "event_date": "2026-12-09",
          "label": "FOMC (Dec)",
          "type": "fomc",
          "notes": "",
          "is_past": false
        }
      ]
    },
    "Payrolls": {
      "contract_series": "KXPAYROLLS-26JUN",
      "latest_run": "2026-06-13T08:00:06.062947+00:00",
      "implied_mean": 97825.0,
      "std_dev": 38872.6366,
      "skewness": -1.7761,
      "market_volume_usd": 74090.0,
      "days_to_event": 19,
      "trend": [
        {
          "timestamp": "2026-05-30T14:00:00.763285+00:00",
          "implied_mean": 78225.0,
          "std_dev": 60421.7417,
          "skewness": -0.73
        },
        {
          "timestamp": "2026-05-30T20:00:00.612362+00:00",
          "implied_mean": 77925.0,
          "std_dev": 59311.7347,
          "skewness": -0.7003
        },
        {
          "timestamp": "2026-05-31T02:00:00.812212+00:00",
          "implied_mean": 78875.0,
          "std_dev": 59283.6139,
          "skewness": -0.7342
        },
        {
          "timestamp": "2026-05-31T08:00:00.964058+00:00",
          "implied_mean": 81950.0,
          "std_dev": 59578.2888,
          "skewness": -0.804
        },
        {
          "timestamp": "2026-05-31T14:00:01.418772+00:00",
          "implied_mean": 82875.0,
          "std_dev": 60024.344,
          "skewness": -0.8178
        },
        {
          "timestamp": "2026-05-31T20:00:01.591951+00:00",
          "implied_mean": 84150.0,
          "std_dev": 60618.9121,
          "skewness": -0.8402
        },
        {
          "timestamp": "2026-06-01T02:00:05.631255+00:00",
          "implied_mean": 83200.0,
          "std_dev": 60320.063,
          "skewness": -0.8329
        },
        {
          "timestamp": "2026-06-01T08:00:00.435070+00:00",
          "implied_mean": 82300.0,
          "std_dev": 60236.6998,
          "skewness": -0.8012
        },
        {
          "timestamp": "2026-06-01T14:00:01.532592+00:00",
          "implied_mean": 83300.0,
          "std_dev": 60726.7239,
          "skewness": -0.7933
        },
        {
          "timestamp": "2026-06-01T20:00:05.112607+00:00",
          "implied_mean": 81425.0,
          "std_dev": 60742.5458,
          "skewness": -0.7508
        },
        {
          "timestamp": "2026-06-02T02:00:01.395096+00:00",
          "implied_mean": 80425.0,
          "std_dev": 59972.9679,
          "skewness": -0.7076
        },
        {
          "timestamp": "2026-06-02T08:00:01.384066+00:00",
          "implied_mean": 80825.0,
          "std_dev": 60127.0062,
          "skewness": -0.7156
        },
        {
          "timestamp": "2026-06-02T14:00:01.758389+00:00",
          "implied_mean": 81575.0,
          "std_dev": 60382.7945,
          "skewness": -0.7339
        },
        {
          "timestamp": "2026-06-02T20:00:04.326511+00:00",
          "implied_mean": 81700.0,
          "std_dev": 61113.501,
          "skewness": -0.7605
        },
        {
          "timestamp": "2026-06-03T02:00:01.016574+00:00",
          "implied_mean": 78825.0,
          "std_dev": 60125.343,
          "skewness": -0.6774
        },
        {
          "timestamp": "2026-06-03T08:00:04.863048+00:00",
          "implied_mean": 80775.0,
          "std_dev": 60558.5409,
          "skewness": -0.7501
        },
        {
          "timestamp": "2026-06-03T14:00:02.931050+00:00",
          "implied_mean": 83325.0,
          "std_dev": 60617.7109,
          "skewness": -0.7924
        },
        {
          "timestamp": "2026-06-03T20:00:04.396391+00:00",
          "implied_mean": 82450.0,
          "std_dev": 60734.0308,
          "skewness": -0.7399
        },
        {
          "timestamp": "2026-06-04T02:00:05.558270+00:00",
          "implied_mean": 82175.0,
          "std_dev": 60063.1491,
          "skewness": -0.7231
        },
        {
          "timestamp": "2026-06-04T08:00:01.826168+00:00",
          "implied_mean": 82150.0,
          "std_dev": 60616.6438,
          "skewness": -0.7652
        },
        {
          "timestamp": "2026-06-04T14:00:04.825699+00:00",
          "implied_mean": 82675.0,
          "std_dev": 60465.1294,
          "skewness": -0.7384
        },
        {
          "timestamp": "2026-06-04T20:00:02.015947+00:00",
          "implied_mean": 84025.0,
          "std_dev": 61051.1005,
          "skewness": -0.8055
        },
        {
          "timestamp": "2026-06-05T02:00:05.139466+00:00",
          "implied_mean": 83300.0,
          "std_dev": 60473.0105,
          "skewness": -0.7506
        },
        {
          "timestamp": "2026-06-05T08:00:05.406934+00:00",
          "implied_mean": 83025.0,
          "std_dev": 59826.0969,
          "skewness": -0.6992
        },
        {
          "timestamp": "2026-06-05T14:00:05.529464+00:00",
          "implied_mean": 68400.0,
          "std_dev": 60079.6555,
          "skewness": -0.6109
        },
        {
          "timestamp": "2026-06-05T20:00:03.259677+00:00",
          "implied_mean": 87800.0,
          "std_dev": 51720.7405,
          "skewness": -1.2315
        },
        {
          "timestamp": "2026-06-06T02:00:02.750302+00:00",
          "implied_mean": 81725.0,
          "std_dev": 55113.1733,
          "skewness": -0.8624
        },
        {
          "timestamp": "2026-06-06T08:00:05.063210+00:00",
          "implied_mean": 92175.0,
          "std_dev": 50143.1139,
          "skewness": -1.5537
        },
        {
          "timestamp": "2026-06-06T14:00:04.115414+00:00",
          "implied_mean": 91600.0,
          "std_dev": 50569.9021,
          "skewness": -1.5167
        },
        {
          "timestamp": "2026-06-06T20:00:05.989113+00:00",
          "implied_mean": 91400.0,
          "std_dev": 50595.6026,
          "skewness": -1.5025
        },
        {
          "timestamp": "2026-06-07T02:00:03.141352+00:00",
          "implied_mean": 88600.0,
          "std_dev": 51028.5704,
          "skewness": -1.3014
        },
        {
          "timestamp": "2026-06-07T08:00:04.590402+00:00",
          "implied_mean": 89900.0,
          "std_dev": 50178.332,
          "skewness": -1.411
        },
        {
          "timestamp": "2026-06-07T14:00:03.779191+00:00",
          "implied_mean": 88500.0,
          "std_dev": 51123.6247,
          "skewness": -1.2828
        },
        {
          "timestamp": "2026-06-07T20:00:04.873686+00:00",
          "implied_mean": 88750.0,
          "std_dev": 50642.7438,
          "skewness": -1.2594
        },
        {
          "timestamp": "2026-06-08T02:00:05.484895+00:00",
          "implied_mean": 90925.0,
          "std_dev": 48230.7669,
          "skewness": -1.3923
        },
        {
          "timestamp": "2026-06-08T08:00:05.061809+00:00",
          "implied_mean": 91625.0,
          "std_dev": 47522.8563,
          "skewness": -1.4438
        },
        {
          "timestamp": "2026-06-08T14:00:05.596057+00:00",
          "implied_mean": 96850.0,
          "std_dev": 45613.3478,
          "skewness": -1.8666
        },
        {
          "timestamp": "2026-06-08T20:00:05.493883+00:00",
          "implied_mean": 99825.0,
          "std_dev": 44451.1741,
          "skewness": -2.021
        },
        {
          "timestamp": "2026-06-09T02:00:06.083278+00:00",
          "implied_mean": 99325.0,
          "std_dev": 44782.6068,
          "skewness": -1.958
        },
        {
          "timestamp": "2026-06-09T08:00:04.768805+00:00",
          "implied_mean": 98625.0,
          "std_dev": 45519.7416,
          "skewness": -1.873
        },
        {
          "timestamp": "2026-06-09T14:00:04.970342+00:00",
          "implied_mean": 98125.0,
          "std_dev": 45295.3847,
          "skewness": -1.8746
        },
        {
          "timestamp": "2026-06-09T20:00:05.165364+00:00",
          "implied_mean": 97825.0,
          "std_dev": 45546.2059,
          "skewness": -1.8398
        },
        {
          "timestamp": "2026-06-10T02:00:05.357584+00:00",
          "implied_mean": 97900.0,
          "std_dev": 45500.989,
          "skewness": -1.8203
        },
        {
          "timestamp": "2026-06-10T08:00:00.946087+00:00",
          "implied_mean": 98425.0,
          "std_dev": 44955.0539,
          "skewness": -1.8596
        },
        {
          "timestamp": "2026-06-10T14:00:05.466072+00:00",
          "implied_mean": 98175.0,
          "std_dev": 44032.4525,
          "skewness": -1.8351
        },
        {
          "timestamp": "2026-06-10T20:00:06.379219+00:00",
          "implied_mean": 97250.0,
          "std_dev": 44437.456,
          "skewness": -1.7207
        },
        {
          "timestamp": "2026-06-11T02:00:05.752474+00:00",
          "implied_mean": 97925.0,
          "std_dev": 44699.0702,
          "skewness": -1.7276
        },
        {
          "timestamp": "2026-06-11T08:00:06.014991+00:00",
          "implied_mean": 96725.0,
          "std_dev": 44060.6046,
          "skewness": -1.7432
        },
        {
          "timestamp": "2026-06-11T14:00:06.181430+00:00",
          "implied_mean": 97075.0,
          "std_dev": 43253.692,
          "skewness": -1.7356
        },
        {
          "timestamp": "2026-06-11T20:00:04.232199+00:00",
          "implied_mean": 97525.0,
          "std_dev": 43251.4378,
          "skewness": -1.7571
        },
        {
          "timestamp": "2026-06-12T02:00:06.027300+00:00",
          "implied_mean": 98050.0,
          "std_dev": 43323.7521,
          "skewness": -1.7834
        },
        {
          "timestamp": "2026-06-12T08:00:06.232905+00:00",
          "implied_mean": 100025.0,
          "std_dev": 39535.5773,
          "skewness": -1.8766
        },
        {
          "timestamp": "2026-06-12T14:00:05.441161+00:00",
          "implied_mean": 99200.0,
          "std_dev": 39880.8851,
          "skewness": -1.808
        },
        {
          "timestamp": "2026-06-12T20:00:01.621394+00:00",
          "implied_mean": 98100.0,
          "std_dev": 39626.5694,
          "skewness": -1.7311
        },
        {
          "timestamp": "2026-06-13T02:00:04.953326+00:00",
          "implied_mean": 98100.0,
          "std_dev": 39134.5755,
          "skewness": -1.7657
        },
        {
          "timestamp": "2026-06-13T08:00:06.062947+00:00",
          "implied_mean": 97825.0,
          "std_dev": 38872.6366,
          "skewness": -1.7761
        }
      ],
      "distribution": [
        {
          "label": "\u2265 125,000k jobs",
          "strike": 125000.0,
          "probability": 0.43,
          "yes_price": 0.43,
          "volume": 0
        },
        {
          "label": "100,000k\u2013125,000k jobs",
          "strike": 100000.0,
          "probability": 0.2,
          "yes_price": 0.63,
          "volume": 0
        },
        {
          "label": "90,000k\u2013100,000k jobs",
          "strike": 90000.0,
          "probability": 0.12,
          "yes_price": 0.75,
          "volume": 0
        }
      ],
      "label": "Payrolls",
      "is_probability": false,
      "annotations": [
        {
          "event_date": "2026-06-05",
          "label": "Payrolls (May)",
          "type": "payrolls",
          "notes": "",
          "is_past": true
        },
        {
          "event_date": "2026-07-02",
          "label": "Payrolls (Jun)",
          "type": "payrolls",
          "notes": "",
          "is_past": false
        },
        {
          "event_date": "2026-08-07",
          "label": "Payrolls (Jul)",
          "type": "payrolls",
          "notes": "",
          "is_past": false
        },
        {
          "event_date": "2026-09-04",
          "label": "Payrolls (Aug)",
          "type": "payrolls",
          "notes": "",
          "is_past": false
        },
        {
          "event_date": "2026-10-02",
          "label": "Payrolls (Sep)",
          "type": "payrolls",
          "notes": "",
          "is_past": false
        },
        {
          "event_date": "2026-11-06",
          "label": "Payrolls (Oct)",
          "type": "payrolls",
          "notes": "",
          "is_past": false
        },
        {
          "event_date": "2026-12-04",
          "label": "Payrolls (Nov)",
          "type": "payrolls",
          "notes": "",
          "is_past": false
        }
      ]
    }
  },
  "accuracy": {
    "Payrolls": {
      "label": "Payrolls",
      "release_count": 2,
      "mae": 71922.91665,
      "rmse": 74263.57693939334,
      "fed_paper_mae": null,
      "releases": [
        {
          "release_date": "2026-06-04",
          "run_date": "2026-06-08",
          "contract_series": "KXPAYROLLS-26MAY",
          "kalshi_implied_mean": 81579.1667,
          "actual_value": 172000.0,
          "error": -90420.8333,
          "abs_error": 90420.8333,
          "days_before": 3,
          "readings_in_window": 12
        },
        {
          "release_date": "2026-05-07",
          "run_date": "2026-05-12",
          "contract_series": "KXPAYROLLS-26APR",
          "kalshi_implied_mean": 61575.0,
          "actual_value": 115000.0,
          "error": -53425.0,
          "abs_error": 53425.0,
          "days_before": 3,
          "readings_in_window": 5
        }
      ]
    },
    "Core_CPI_MoM": {
      "label": "Core CPI (MoM)",
      "release_count": 2,
      "mae": 0.03445,
      "rmse": 0.038394075063738674,
      "fed_paper_mae": 0.07,
      "releases": [
        {
          "release_date": "2026-05-11",
          "run_date": "2026-06-01",
          "contract_series": "KXCPICORE-26APR",
          "kalshi_implied_mean": 0.3251,
          "actual_value": 0.3765,
          "error": -0.0514,
          "abs_error": 0.0514,
          "days_before": 3,
          "readings_in_window": 12
        },
        {
          "release_date": "2026-04-09",
          "run_date": "2026-06-01",
          "contract_series": "KXCPICORE-26MAR",
          "kalshi_implied_mean": 0.2133,
          "actual_value": 0.1958,
          "error": 0.0175,
          "abs_error": 0.0175,
          "days_before": 3,
          "readings_in_window": 6
        }
      ]
    },
    "CPI": {
      "label": "CPI (YoY)",
      "release_count": 2,
      "mae": 0.08135,
      "rmse": 0.10034632529395383,
      "fed_paper_mae": 0.069,
      "releases": [
        {
          "release_date": "2026-05-11",
          "run_date": "2026-06-01",
          "contract_series": "KXCPIYOY-26APR",
          "kalshi_implied_mean": 3.6391,
          "actual_value": 3.7792,
          "error": -0.1401,
          "abs_error": 0.1401,
          "days_before": 3,
          "readings_in_window": 12
        },
        {
          "release_date": "2026-04-09",
          "run_date": "2026-06-01",
          "contract_series": "KXCPIYOY-26MAR",
          "kalshi_implied_mean": 3.2634,
          "actual_value": 3.286,
          "error": -0.0226,
          "abs_error": 0.0226,
          "days_before": 3,
          "readings_in_window": 7
        }
      ]
    },
    "GDP": {
      "label": "GDP Growth",
      "release_count": 1,
      "mae": 0.3556,
      "rmse": 0.3556,
      "fed_paper_mae": null,
      "releases": [
        {
          "release_date": "2026-04-29",
          "run_date": "2026-05-04",
          "contract_series": "KXGDP-26APR30",
          "kalshi_implied_mean": 2.3556,
          "actual_value": 2.0,
          "error": 0.3556,
          "abs_error": 0.3556,
          "days_before": 3,
          "readings_in_window": 12
        }
      ]
    }
  }
}